aiocometd_ng/__init__.py
aiocometd_ng/_metadata.py
aiocometd_ng/client.py
aiocometd_ng/constants.py
aiocometd_ng/exceptions.py
aiocometd_ng/extensions.py
aiocometd_ng/py.typed
aiocometd_ng/typing.py
aiocometd_ng/utils.py
aiocometd_ng/transports/__init__.py
aiocometd_ng/transports/abc.py
aiocometd_ng/transports/base.py
aiocometd_ng/transports/long_polling.py
aiocometd_ng/transports/registry.py
aiocometd_ng/transports/websocket.py
aiocometd_ng-0.5.6.dist-info/LICENSE.txt
aiocometd_ng-0.5.6.dist-info/METADATA
aiocometd_ng-0.5.6.dist-info/WHEEL
aiocometd_ng-0.5.6.dist-info/top_level.txt
aiocometd_ng-0.5.6.dist-info/RECORD
