Metadata-Version: 2.1
Name: aiocometd-ng
Version: 0.5.6
Summary: CometD client for asyncio
Home-page: https://github.com/bensnyde/aiocometd-ng
Author: Benton Snyder
Author-email: benton@bensnyde.me
License: MIT
Project-URL: CI, https://travis-ci.org/robertmrk/aiocometd
Project-URL: Coverage, https://coveralls.io/github/robertmrk/aiocometd
Project-URL: Docs, http://aiocometd.readthedocs.io/
Keywords: asyncio aiohttp comet cometd bayeux push streaming
Classifier: Programming Language :: Python
Classifier: Programming Language :: Python :: 3
Classifier: Programming Language :: Python :: 3.10
Classifier: Programming Language :: Python :: Implementation :: CPython
Classifier: Framework :: AsyncIO
Classifier: License :: OSI Approved :: MIT License
Requires-Python: >=3.10.0
License-File: LICENSE.txt
Requires-Dist: aiohttp >=3.1
Provides-Extra: dev
Requires-Dist: asynctest <1.0.0,>=0.12.0 ; extra == 'dev'
Requires-Dist: coverage <5.0,>=4.5 ; extra == 'dev'
Requires-Dist: docker >=3.5.1 ; extra == 'dev'
Requires-Dist: flake8 ; extra == 'dev'
Requires-Dist: pylint ; extra == 'dev'
Requires-Dist: mypy ; extra == 'dev'
Requires-Dist: Sphinx <2.0,>=1.7 ; extra == 'dev'
Requires-Dist: sphinxcontrib-asyncio >=0.2.0 ; extra == 'dev'
Requires-Dist: sphinx-autodoc-typehints ; extra == 'dev'
Requires-Dist: aioconsole <1.0.0,>=0.1.7 ; extra == 'dev'
Provides-Extra: docs
Requires-Dist: Sphinx <2.0,>=1.7 ; extra == 'docs'
Requires-Dist: sphinxcontrib-asyncio >=0.2.0 ; extra == 'docs'
Requires-Dist: sphinx-autodoc-typehints ; extra == 'docs'
Provides-Extra: examples
Requires-Dist: aioconsole <1.0.0,>=0.1.7 ; extra == 'examples'
Provides-Extra: tests
Requires-Dist: asynctest <1.0.0,>=0.12.0 ; extra == 'tests'
Requires-Dist: coverage <5.0,>=4.5 ; extra == 'tests'
Requires-Dist: docker >=3.5.1 ; extra == 'tests'
Requires-Dist: flake8 ; extra == 'tests'
Requires-Dist: pylint ; extra == 'tests'
Requires-Dist: mypy ; extra == 'tests'
